{
  "$schema": "https://developer.microsoft.com/json-schemas/fabric/item/report/definition/visualContainer/2.1.0/schema.json",
  "name": "907ee3efccb7db742290",
  "position": {
    "x": 16,
    "y": 111.99999999999999,
    "z": 0,
    "height": 608,
    "width": 1264,
    "tabOrder": 1000
  },
  "visual": {
    "visualType": "textbox",
    "objects": {
      "general": [
        {
          "properties": {
            "paragraphs": [
              {
                "textRuns": [
                  {
                    "value": ""
                  }
                ],
                "horizontalTextAlignment": "center"
              },
              {
                "textRuns": [
                  {
                    "value": "About This Dashboard",
                    "textStyle": {
                      "fontWeight": "bold",
                      "fontSize": "18pt"
                    }
                  }
                ],
                "horizontalTextAlignment": "center"
              },
              {
                "textRuns": [
                  {
                    "value": "Purpose",
                    "textStyle": {
                      "fontWeight": "bold",
                      "fontSize": "16pt"
                    }
                  }
                ]
              },
              {
                "textRuns": [
                  {
                    "value": ""
                  }
                ]
              },
              {
                "textRuns": [
                  {
                    "value": "The Construction Operations Dashboard offers a centralized view of project performance across multiple sites and customers. It empowers stakeholders to monitor critical KPIs related to scheduling performance, material delivery, design acceptance, and staff readiness.",
                    "textStyle": {
                      "fontSize": "16pt"
                    }
                  }
                ]
              },
              {
                "textRuns": [
                  {
                    "value": ""
                  }
                ]
              },
              {
                "textRuns": [
                  {
                    "value": "Key Metrics Included:",
                    "textStyle": {
                      "fontWeight": "bold",
                      "fontSize": "16pt"
                    }
                  }
                ]
              },
              {
                "textRuns": [
                  {
                    "value": ""
                  }
                ]
              },
              {
                "textRuns": [
                  {
                    "value": "Total Buildings",
                    "textStyle": {
                      "fontWeight": "bold",
                      "fontSize": "16pt"
                    }
                  },
                  {
                    "value": ": Number of buildings currently tracked in the dataset.",
                    "textStyle": {
                      "fontSize": "16pt"
                    }
                  }
                ],
                "listType": "bullet"
              },
              {
                "textRuns": [
                  {
                    "value": "Early Start",
                    "textStyle": {
                      "fontWeight": "bold",
                      "fontSize": "16pt"
                    }
                  },
                  {
                    "value": ": Projects that began ahead of their planned start date.",
                    "textStyle": {
                      "fontSize": "16pt"
                    }
                  }
                ],
                "listType": "bullet"
              },
              {
                "textRuns": [
                  {
                    "value": "On Time Start",
                    "textStyle": {
                      "fontWeight": "bold",
                      "fontSize": "16pt"
                    }
                  },
                  {
                    "value": ": Projects that started exactly on the planned date.",
                    "textStyle": {
                      "fontSize": "16pt"
                    }
                  }
                ],
                "listType": "bullet"
              },
              {
                "textRuns": [
                  {
                    "value": "Delayed Start",
                    "textStyle": {
                      "fontWeight": "bold",
                      "fontSize": "16pt"
                    }
                  },
                  {
                    "value": ": Projects that began later than scheduled.",
                    "textStyle": {
                      "fontSize": "16pt"
                    }
                  }
                ],
                "listType": "bullet"
              },
              {
                "textRuns": [
                  {
                    "value": "Unknown Status",
                    "textStyle": {
                      "fontWeight": "bold",
                      "fontSize": "16pt"
                    }
                  },
                  {
                    "value": ": Projects with missing or undefined start dates.",
                    "textStyle": {
                      "fontSize": "16pt"
                    }
                  }
                ],
                "listType": "bullet"
              },
              {
                "textRuns": [
                  {
                    "value": "Within Schedule",
                    "textStyle": {
                      "fontWeight": "bold",
                      "fontSize": "16pt"
                    }
                  },
                  {
                    "value": ": Projects considered on track (includes both early and on-time starts).",
                    "textStyle": {
                      "fontSize": "16pt"
                    }
                  }
                ],
                "listType": "bullet"
              },
              {
                "textRuns": [
                  {
                    "value": "Start to Inspection < 30 Days",
                    "textStyle": {
                      "fontWeight": "bold",
                      "fontSize": "16pt"
                    }
                  },
                  {
                    "value": ": Projects with fewer than 30 days between actual start and inspection dates.",
                    "textStyle": {
                      "fontSize": "16pt"
                    }
                  }
                ],
                "listType": "bullet"
              },
              {
                "textRuns": [
                  {
                    "value": "Gravel Delivered %",
                    "textStyle": {
                      "fontWeight": "bold",
                      "fontSize": "16pt"
                    }
                  },
                  {
                    "value": ": Gravel delivered as a percentage of the planned quantity.",
                    "textStyle": {
                      "fontSize": "16pt"
                    }
                  }
                ],
                "listType": "bullet"
              },
              {
                "textRuns": [
                  {
                    "value": "Sand Delivered %",
                    "textStyle": {
                      "fontWeight": "bold",
                      "fontSize": "16pt"
                    }
                  },
                  {
                    "value": ": Sand delivered as a percentage of the planned quantity.",
                    "textStyle": {
                      "fontSize": "16pt"
                    }
                  }
                ],
                "listType": "bullet"
              },
              {
                "textRuns": [
                  {
                    "value": ""
                  }
                ]
              }
            ]
          }
        }
      ]
    },
    "drillFilterOtherVisuals": true
  }
}